jarguments/__init__.py
jarguments/create.py
jarguments/handle.py
jarguments/parse.py
jarguments-0.3.0.dist-info/LICENSE
jarguments-0.3.0.dist-info/METADATA
jarguments-0.3.0.dist-info/WHEEL
jarguments-0.3.0.dist-info/top_level.txt
jarguments-0.3.0.dist-info/zip-safe
jarguments-0.3.0.dist-info/RECORD
