Metadata-Version: 2.1
Name: jarguments
Version: 0.3.0
Summary: Provides a straightforward way to create command line arguments.
Home-page: https://github.com/silvncr/jarguments
Author: silvncr
License: MIT
Classifier: Development Status :: 4 - Beta
Classifier: License :: OSI Approved :: MIT License
Classifier: Operating System :: OS Independent
Requires-Python: >=3.8
License-File: LICENSE
